{
  "id": "mrp3a5px6sca",
  "type": "reference",
  "title": "Gene set: primate_ampl_multi",
  "genes": [
    "ARMCX6",
    "ATXN3L",
    "C16ORF89",
    "CENPVL",
    "CSAG",
    "CT45A",
    "CT47",
    "CT55",
    "CT83",
    "CTAG",
    "CXORF49",
    "CXORF51B",
    "DDX53",
    "DMRTC1",
    "EOLA1",
    "F8A",
    "FAM156A",
    "FAM156B",
    "FAM236",
    "FAM47A",
    "FAM47B",
    "FAM9A",
    "FAM9B",
    "GAGE",
    "H2AB",
    "H2BW",
    "HMGB",
    "HSFX1",
    "HSFX2",
    "HSFX3",
    "HSFX4",
    "IKBKG",
    "LAGE3",
    "MAGEA",
    "MAGEB",
    "MAGED",
    "NXF",
    "OPN1",
    "PABPC",
    "PAGE",
    "PNMA",
    "PWWP3B",
    "RHOXF2",
    "RPL10",
    "SAGE1",
    "SCML1",
    "SPANXN",
    "SPIN",
    "SSX",
    "TCP11X",
    "TEX28",
    "TMEM185A",
    "TMLHE",
    "TMSB15B",
    "TRMT2B",
    "USP27X",
    "VCX",
    "XAGE1A",
    "XAGE1B",
    "XAGE2",
    "XAGE3",
    "XAGE5",
    "ZNF"
  ],
  "tags": [
    "primate_ampl_multi",
    "gene-set"
  ],
  "source": "https://doi.org/10.1038/s41559-022-01974-x",
  "connection": false,
  "archived": false,
  "pinned": false,
  "due": "",
  "date": "2026-07-17T15:25:00.000Z",
  "synced": false
}